{
  "version": 1,
  "platform": "alptis",
  "slug": "alptis_login",
  "name": "Connexion Alptis",
  "active": true,
  "steps": [
    {
      "type": "goto",
      "url": "https://pro.alptis.org/",
      "screenshot_label": "accueil",
      "timeout_ms": 15000
    },
    {
      "type": "waitFor",
      "selector": "#username",
      "screenshot_label": "login-form",
      "timeout_ms": 10000
    },
    {
      "type": "fill",
      "selector": "#username",
      "value": "{username}",
      "screenshot_label": "fill-user"
    },
    {
      "type": "fill",
      "selector": "#password",
      "value": "{password}",
      "screenshot_label": "fill-pass"
    },
    {
      "type": "click",
      "selector": "button[type=\"submit\"]",
      "screenshot_label": "submit"
    },
    {
      "type": "sleep",
      "timeout_ms": 1500
    },
    {
      "type": "tryClick",
      "selector": "#axeptio_btn_acceptAll",
      "screenshot_label": "accept-axeptio",
      "timeout_ms": 1500
    },
    {
      "type": "screenshot",
      "screenshot_label": "after-submit"
    }
  ]
}
